rosely/__init__.py
rosely/windrose.py
Rosely-0.0.2.post3.dist-info/LICENSE
Rosely-0.0.2.post3.dist-info/METADATA
Rosely-0.0.2.post3.dist-info/WHEEL
Rosely-0.0.2.post3.dist-info/top_level.txt
Rosely-0.0.2.post3.dist-info/RECORD
